junit_xml.py
logger.py
publish_tar.py
publish_tar-2.2.0.dist-info/METADATA
publish_tar-2.2.0.dist-info/WHEEL
publish_tar-2.2.0.dist-info/entry_points.txt
publish_tar-2.2.0.dist-info/top_level.txt
publish_tar-2.2.0.dist-info/RECORD
