Metadata-Version: 2.4
Name: publish-tar
Version: 2.2.0
Summary: publish test results to tar.
Author-email: qun <qun.chen@hexagon.com>
License: MIT License
Keywords: junit
Requires-Python: >=3.0
